stillsuit/__init__.py
stillsuit/_version.py
stillsuit/bin/__init__.py
stillsuit/bin/merge_reduce.py
stillsuit/bin/plot.py
stillsuit/bin/show.py
stillsuit-0.1.0.dist-info/licenses/LICENSE
stillsuit-0.1.0.dist-info/METADATA
stillsuit-0.1.0.dist-info/WHEEL
stillsuit-0.1.0.dist-info/entry_points.txt
stillsuit-0.1.0.dist-info/top_level.txt
stillsuit-0.1.0.dist-info/RECORD
