Metadata-Version: 2.4
Name: stillsuit
Version: 0.1.0
Summary: A place to store all that is precious.
Author-email: Chad Hanna <crh184@psu.edu>
Project-URL: Homepage, https://git.ligo.org/greg/stillsuit
Project-URL: Documentation, https://greg.docs.ligo.org/stillsuit
Project-URL: Issues, https://git.ligo.org/greg/stillsuit/issues
Classifier: Programming Language :: Python :: 3
Classifier: License :: OSI Approved :: Mozilla Public License 2.0 (MPL 2.0)
Classifier: Operating System :: OS Independent
Requires-Python: >=3.9
License-File: LICENSE
Requires-Dist: numpy
Requires-Dist: pyyaml
Provides-Extra: docs
Requires-Dist: mkdocs; extra == "docs"
Requires-Dist: mkdocs-material; extra == "docs"
Requires-Dist: mkdocstrings[python]; extra == "docs"
Provides-Extra: test
Requires-Dist: pytest; extra == "test"
Requires-Dist: pytest-cov; extra == "test"
Provides-Extra: lint
Requires-Dist: black; extra == "lint"
Requires-Dist: flake8; extra == "lint"
Requires-Dist: flake8-pyproject; extra == "lint"
Requires-Dist: isort; extra == "lint"
Provides-Extra: dev
Requires-Dist: stillsuit[docs]; extra == "dev"
Requires-Dist: stillsuit[lint]; extra == "dev"
Requires-Dist: stillsuit[test]; extra == "dev"
Dynamic: license-file
